py_enum/__init__.py
py_enum/choice.py
py_enum/choice.pyi
py_enum/py.typed
py_enum-2.1.1.dist-info/licenses/LICENSE
py_enum-2.1.1.dist-info/METADATA
py_enum-2.1.1.dist-info/WHEEL
py_enum-2.1.1.dist-info/top_level.txt
py_enum-2.1.1.dist-info/RECORD
