Metadata-Version: 2.4
Name: py-enum
Version: 2.1.1
Summary: enums for choices fields
Home-page: https://github.com/SkylerHu/py-enum.git
Author: SkylerHu
Author-email: skylerhu@qq.com
License: MIT Licence
Keywords: python,enum,ChoiceEnum,enumerate
Platform: any
Classifier: Development Status :: 4 - Beta
Classifier: Intended Audience :: Developers
Classifier: License :: OSI Approved :: MIT License
Classifier: Programming Language :: Python :: 3
Requires-Python: >=3.6
License-File: LICENSE
Dynamic: author
Dynamic: author-email
Dynamic: classifier
Dynamic: description
Dynamic: description-content-type
Dynamic: home-page
Dynamic: keywords
Dynamic: license
Dynamic: license-file
Dynamic: platform
Dynamic: requires-python
Dynamic: summary
